_generics/__init__.py
_generics/delegated.py
_generics/exceptions.py
_generics/private.py
generics/__init__.py
generics/exceptions.py
generics-5.0.0.dist-info/LICENSE
generics-5.0.0.dist-info/WHEEL
generics-5.0.0.dist-info/METADATA
generics-5.0.0.dist-info/RECORD
