Metadata-Version: 2.1
Name: generics
Version: 5.0.0
Summary: A classy toolkit designed with OOP in mind.
Home-page: https://pypi.org/project/generics
License: BSD-2-Clause
Author: Josiah Kaviani
Author-email: proofit404@gmail.com
Classifier: License :: OSI Approved :: BSD License
Classifier: Programming Language :: Python :: 2
Classifier: Programming Language :: Python :: 2.7
Classifier: Programming Language :: Python :: 3
Classifier: Programming Language :: Python :: 3.4
Classifier: Programming Language :: Python :: 3.5
Classifier: Programming Language :: Python :: 3.6
Classifier: Programming Language :: Python :: 3.7
Classifier: Programming Language :: Python :: 3.8
Classifier: Programming Language :: Python :: 3.9
Classifier: Programming Language :: Python :: 3.10
Classifier: Programming Language :: Python :: 3.11
Classifier: Programming Language :: Python :: Implementation :: CPython
Classifier: Programming Language :: Python :: Implementation :: PyPy
Project-URL: Changelog, https://proofit404.github.io/generics/changelog
Project-URL: Documentation, https://proofit404.github.io/generics
Project-URL: Issues, https://github.com/proofit404/generics/issues
Project-URL: Repository, https://github.com/proofit404/generics
Project-URL: Twitter, https://twitter.com/proofit404
